sigopt_spark/__init__.py
sigopt_spark/estimator.py
sigopt_spark-1.0.1.dist-info/METADATA
sigopt_spark-1.0.1.dist-info/WHEEL
sigopt_spark-1.0.1.dist-info/top_level.txt
sigopt_spark-1.0.1.dist-info/RECORD
