Metadata-Version: 2.1
Name: sigopt-spark
Version: 1.0.1
Summary: SigOpt Pyspark Integration
Home-page: https://sigopt.com/
Author: SigOpt
Author-email: support@sigopt.com
License: UNKNOWN
Platform: UNKNOWN
Classifier: Development Status :: 5 - Production/Stable
Classifier: Intended Audience :: Developers
Classifier: License :: OSI Approved :: Apache Software License
Classifier: Operating System :: OS Independent
Classifier: Programming Language :: Python
Classifier: Topic :: Software Development :: Libraries :: Python Modules
Requires-Dist: sigopt (>=5.3.1)
Requires-Dist: pyspark (>=2.0.0)
